README.md
global_reference/_run_jobs_global_reference.ipynb
global_reference/_run_jobs_global_reference.py
global_reference/autogenerated/python/readme.md
global_reference/autogenerated/python/reference_data_cdh_athena_class_create.py
global_reference/autogenerated/python/reference_data_cdh_athena_class_list.py
global_reference/autogenerated/python/reference_data_cdh_reference_concept_class_create_view.py
global_reference/autogenerated/sql/cdh_athena_class_create.sql
global_reference/autogenerated/sql/cdh_athena_class_list.sql
global_reference/autogenerated/sql/cdh_reference_concept_class_create_view.sql
global_reference/autogenerated/sql/readme.md
global_reference/config/bronze_sps_config_columns.csv
global_reference/config/bronze_sps_config_datasets.csv
global_reference/config/bronze_sps_config_datasets_1.csv
global_reference/config/bronze_sps_config_jobs.csv
global_reference/config/bronze_sps_config_workflows.csv
global_reference/config/config.dev.json
global_reference/utility/delete_and_vacuum_edav_dev_cdh.cdh_reference.py
pyproject.toml
setup.cfg
setup.py
cdh_global_reference-202403.0.7.dist-info/METADATA
cdh_global_reference-202403.0.7.dist-info/WHEEL
cdh_global_reference-202403.0.7.dist-info/entry_points.txt
cdh_global_reference-202403.0.7.dist-info/RECORD
