Metadata-Version: 2.1
Name: cdh-global-reference
Version: 202403.0.7
Summary: CDC Data Hub Reference Data Accelerator Python
Home-page: https://pypi.org/project/cdh-global-reference
License: Apache
Author: John Bowyer
Author-email: zfi4@cdc.gov
Requires-Python: >=3.10,<4.0
Classifier: Development Status :: 4 - Beta
Classifier: Environment :: Console
Classifier: Intended Audience :: Developers
Classifier: License :: Other/Proprietary License
Classifier: Operating System :: OS Independent
Classifier: Programming Language :: Python
Classifier: Programming Language :: Python :: 3
Classifier: Programming Language :: Python :: 3.10
Classifier: Programming Language :: Python :: 3.11
Requires-Dist: mlflow (>=2.10.0,<3.0.0)
Requires-Dist: pytest (>=7.1.2,<8.0.0)
Project-URL: Repository, https://github.com/cdcent/cdh-global-reference
